r2inspect/__init__.py
r2inspect/__main__.py
r2inspect/__version__.py
r2inspect/cli_main.py
r2inspect/config.py
r2inspect/lazy_loader.py
r2inspect/abstractions/__init__.py
r2inspect/abstractions/analysis_result.py
r2inspect/abstractions/base_analyzer.py
r2inspect/abstractions/hashing_strategy.py
r2inspect/adapters/__init__.py
r2inspect/adapters/r2pipe_adapter.py
r2inspect/adapters/validation.py
r2inspect/cli/__init__.py
r2inspect/cli/analysis_runner.py
r2inspect/cli/batch_output.py
r2inspect/cli/batch_processing.py
r2inspect/cli/display.py
r2inspect/cli/interactive.py
r2inspect/cli/validators.py
r2inspect/cli/commands/__init__.py
r2inspect/cli/commands/analyze_command.py
r2inspect/cli/commands/base.py
r2inspect/cli/commands/batch_command.py
r2inspect/cli/commands/config_command.py
r2inspect/cli/commands/interactive_command.py
r2inspect/cli/commands/version_command.py
r2inspect/config_schemas/__init__.py
r2inspect/config_schemas/builder.py
r2inspect/config_schemas/schemas.py
r2inspect/core/__init__.py
r2inspect/core/constants.py
r2inspect/core/file_validator.py
r2inspect/core/inspector.py
r2inspect/core/pipeline_builder.py
r2inspect/core/r2_session.py
r2inspect/core/result_aggregator.py
r2inspect/error_handling/__init__.py
r2inspect/error_handling/policies.py
r2inspect/error_handling/presets.py
r2inspect/error_handling/unified_handler.py
r2inspect/interfaces/__init__.py
r2inspect/interfaces/binary_analyzer.py
r2inspect/modules/__init__.py
r2inspect/modules/anti_analysis.py
r2inspect/modules/authenticode_analyzer.py
r2inspect/modules/binbloom_analyzer.py
r2inspect/modules/bindiff_analyzer.py
r2inspect/modules/binlex_analyzer.py
r2inspect/modules/ccbhash_analyzer.py
r2inspect/modules/compiler_detector.py
r2inspect/modules/crypto_analyzer.py
r2inspect/modules/elf_analyzer.py
r2inspect/modules/exploit_mitigation_analyzer.py
r2inspect/modules/export_analyzer.py
r2inspect/modules/function_analyzer.py
r2inspect/modules/impfuzzy_analyzer.py
r2inspect-2.0.0.dist-info/licenses/LICENSE
r2inspect-2.0.0.dist-info/METADATA
r2inspect-2.0.0.dist-info/WHEEL
r2inspect-2.0.0.dist-info/entry_points.txt
r2inspect-2.0.0.dist-info/top_level.txt
r2inspect-2.0.0.dist-info/RECORD
