Metadata-Version: 2.4
Name: r2inspect
Version: 2.0.0
Summary: Advanced malware analysis tool using radare2 and r2pipe
Home-page: https://github.com/seifreed/r2inspect
Author: Marc Rivero
Author-email: Marc Rivero <mriverolopez@gmail.com>
Maintainer-email: Marc Rivero <mriverolopez@gmail.com>
License: GPL-3.0
Project-URL: Homepage, https://github.com/seifreed/r2inspect
Project-URL: Documentation, https://github.com/seifreed/r2inspect/blob/main/README.md
Project-URL: Repository, https://github.com/seifreed/r2inspect
Project-URL: Issues, https://github.com/seifreed/r2inspect/issues
Project-URL: Changelog, https://github.com/seifreed/r2inspect/releases
Keywords: malware,analysis,radare2,r2pipe,reverse-engineering,security,forensics
Classifier: Development Status :: 4 - Beta
Classifier: Intended Audience :: Developers
Classifier: Intended Audience :: Information Technology
Classifier: Intended Audience :: Science/Research
Classifier: License :: OSI Approved :: GNU General Public License v3 (GPLv3)
Classifier: Operating System :: OS Independent
Classifier: Programming Language :: Python :: 3
Classifier: Programming Language :: Python :: 3.10
Classifier: Programming Language :: Python :: 3.11
Classifier: Programming Language :: Python :: 3.12
Classifier: Programming Language :: Python :: 3.13
Classifier: Topic :: Security
Classifier: Topic :: Software Development :: Libraries :: Python Modules
Classifier: Topic :: System :: Systems Administration
Classifier: Topic :: Utilities
Requires-Python: >=3.8
License-File: LICENSE
Requires-Dist: r2pipe>=1.8.0
Requires-Dist: click>=8.0.0
Requires-Dist: rich>=13.0.0
Requires-Dist: colorlog>=6.8.0
Requires-Dist: pefile>=2023.2.7
Requires-Dist: yara-python>=4.5.0
Requires-Dist: python-magic>=0.4.27
Requires-Dist: pycryptodome>=3.19.0
Requires-Dist: cryptography>=41.0.0
Requires-Dist: psutil>=5.9.0
Requires-Dist: pydantic>=2.5.0
Requires-Dist: pybloom-live>=4.0.0
Requires-Dist: simhash>=2.1.0
Requires-Dist: colorama>=0.4.6
Requires-Dist: tabulate>=0.9.0
Requires-Dist: pyfiglet>=0.8.post1
Requires-Dist: pandas>=1.3.0; python_version < "3.9"
Requires-Dist: pandas>=1.5.0; python_version >= "3.9" and python_version < "3.11"
Requires-Dist: pandas>=2.0.0; python_version >= "3.11"
Requires-Dist: requests>=2.31.0
Provides-Extra: dev
Requires-Dist: black>=23.0.0; extra == "dev"
Requires-Dist: ruff>=0.1.0; extra == "dev"
Requires-Dist: mypy>=1.0.0; extra == "dev"
Requires-Dist: pytest>=7.0.0; extra == "dev"
Requires-Dist: pytest-cov>=4.0.0; extra == "dev"
Requires-Dist: pre-commit>=3.0.0; extra == "dev"
Requires-Dist: bandit>=1.7.0; extra == "dev"
Requires-Dist: mutmut>=2.4.0; extra == "dev"
Provides-Extra: docker
Requires-Dist: pycparser>=2.21; extra == "docker"
Requires-Dist: pyimpfuzzy>=0.1.1; extra == "docker"
Requires-Dist: python-tlsh>=4.5.0; extra == "docker"
Requires-Dist: ssdeep>=3.4; extra == "docker"
Dynamic: author
Dynamic: home-page
Dynamic: license-file
Dynamic: requires-python
